sqlagent_community/Agent.py
sqlagent_community/Builder.py
sqlagent_community/__init__.py
sqlagent_community/memory/ChatManager.py
sqlagent_community/memory/ConversationSummaryBufferMemory.py
sqlagent_community/memory/__init__.py
sqlagent_community/steps/EmbemdSQL.py
sqlagent_community/steps/ExcelSQL.py
sqlagent_community/steps/ExecuteSQL.py
sqlagent_community/steps/GenerateSQL.py
sqlagent_community/steps/LLM.py
sqlagent_community/steps/Search.py
sqlagent_community/steps/__init__.py
sqlagent_community/utils/BuildPromptSQL.py
sqlagent_community/utils/CleanData.py
sqlagent_community/utils/GatewayRouter.py
sqlagent_community/utils/QuestionRewriter.py
sqlagent_community/utils/Rag.py
sqlagent_community/utils/Schema.py
sqlagent_community/utils/__init__.py
sqlagent_community-0.1.3.dist-info/licenses/LICENSE
sqlagent_community-0.1.3.dist-info/METADATA
sqlagent_community-0.1.3.dist-info/WHEEL
sqlagent_community-0.1.3.dist-info/top_level.txt
sqlagent_community-0.1.3.dist-info/RECORD
