Metadata-Version: 2.4
Name: sqlagent-community
Version: 0.1.3
Summary: Conversational Text-to-SQL agent that allows you to ask natural language questions over structured data (Excel → SQLite), using semantic search, automatic SQL generation, safe execution, and LLM-based result interpretation — all with conversation memory and SQL history.
Author-email: Gabriel Cicotoste <gabriel.cicotoste@grupoge21.com>
License: MIT License
Classifier: Programming Language :: Python :: 3
Classifier: License :: OSI Approved :: MIT License
Classifier: Operating System :: OS Independent
Requires-Python: >=3.10
License-File: LICENSE
Dynamic: license-file
